artella/__init__.py
artella/installer/__init__.py
artella/installer/maya/__init__.py
artella/installer/maya/__version__.py
artella/installer/maya/_version.py
artella/installer/maya/artella-installer.json
artella_installer_maya-0.0.3.dist-info/METADATA
artella_installer_maya-0.0.3.dist-info/WHEEL
artella_installer_maya-0.0.3.dist-info/top_level.txt
artella_installer_maya-0.0.3.dist-info/RECORD
