Metadata-Version: 2.1
Name: artella-installer-maya
Version: 0.0.3
Summary: Repository that contains configuration files used by Artella Maya installer.
Home-page: https://github.com/artella/artella-installer-maya
Author: Artella, Inc
Author-email: support@artella.com
License: UNKNOWN
Platform: UNKNOWN
Provides-Extra: dev
Requires-Dist: wheel ; extra == 'dev'
